gluepkg/__init__.py
gluepkg/__main__.py
gluepkg/package.py
gluepkg-1.0.2.dist-info/METADATA
gluepkg-1.0.2.dist-info/WHEEL
gluepkg-1.0.2.dist-info/entry_points.txt
gluepkg-1.0.2.dist-info/top_level.txt
gluepkg-1.0.2.dist-info/RECORD
