Metadata-Version: 2.1
Name: gluepkg
Version: 1.0.2
Summary: Package for AWS Glue Library
Home-page: UNKNOWN
Author: Andreas
Author-email: suekto.andreas@gmail.com
License: UNKNOWN
Platform: UNKNOWN
Requires-Dist: boto3
